s3_tools/__init__.py
s3_tools/buckets/__init__.py
s3_tools/buckets/check.py
s3_tools/buckets/create.py
s3_tools/buckets/delete.py
s3_tools/buckets/list.py
s3_tools/objects/__init__.py
s3_tools/objects/check.py
s3_tools/objects/copy.py
s3_tools/objects/delete.py
s3_tools/objects/download.py
s3_tools/objects/list.py
s3_tools/objects/move.py
s3_tools/objects/presigned_url.py
s3_tools/objects/read.py
s3_tools/objects/upload.py
s3_tools/objects/write.py
s3_tools/utils.py
aws_s3_tools-0.3.0.dist-info/LICENSE
aws_s3_tools-0.3.0.dist-info/METADATA
aws_s3_tools-0.3.0.dist-info/WHEEL
aws_s3_tools-0.3.0.dist-info/RECORD
