Metadata-Version: 2.1
Name: aws-s3-tools
Version: 0.3.0
Summary: AWS S3 tools package
Home-page: https://github.com/dlite-tools/aws-s3-tools
License: MIT
Keywords: aws,s3,tools,package
Author: Daniel Ferrari
Maintainer: Daniel Ferrari, Carlos Alves, Tomás Osório
Requires-Python: >=3.8,<4.0
Classifier: Development Status :: 5 - Production/Stable
Classifier: Intended Audience :: Developers
Classifier: License :: Freely Distributable
Classifier: License :: OSI Approved :: MIT License
Classifier: Natural Language :: English
Classifier: Programming Language :: Python :: 3
Classifier: Programming Language :: Python :: 3.8
Classifier: Programming Language :: Python :: 3.9
Classifier: Programming Language :: Python :: 3.10
Classifier: Programming Language :: Python :: 3.11
Classifier: Programming Language :: Python :: 3.7
Classifier: Topic :: Software Development :: Libraries :: Python Modules
Classifier: Topic :: Utilities
Provides-Extra: progress
Requires-Dist: boto3 (>=1.25,<2.0)
Requires-Dist: rich (>=13,<14) ; extra == "progress"
Requires-Dist: ujson (>=5,<6)
Project-URL: Documentation, https://aws-s3-tools.readthedocs.io/en/latest/index.html
Project-URL: Repository, https://github.com/dlite-tools/aws-s3-tools
